LICENSE
MANIFEST.in
README.rst
setup.py
il2fb/config/ds/__init__.py
il2fb/config/ds/compat.py
il2fb/config/ds/mapping.py
il2fb/config/ds/schemas/__init__.py
il2fb/config/ds/schemas/about.py
il2fb/config/ds/schemas/connection.py
il2fb/config/ds/schemas/console.py
il2fb/config/ds/schemas/constants.py
il2fb/config/ds/schemas/device_link.py
il2fb/config/ds/schemas/events.py
il2fb/config/ds/schemas/helpers.py
il2fb/config/ds/schemas/hud.py
il2fb/config/ds/schemas/interfaces.py
il2fb/config/ds/schemas/misc.py
il2fb/config/ds/schemas/morse.py
il2fb/config/ds/schemas/refly.py
il2fb/config/ds/schemas/statistics.py
il2fb/config/ds/schemas/anticheat/__init__.py
il2fb/config/ds/schemas/anticheat/lags.py
il2fb/config/ds/schemas/anticheat/speedhack.py
il2fb_ds_config.egg-info/PKG-INFO
il2fb_ds_config.egg-info/SOURCES.txt
il2fb_ds_config.egg-info/dependency_links.txt
il2fb_ds_config.egg-info/namespace_packages.txt
il2fb_ds_config.egg-info/not-zip-safe
il2fb_ds_config.egg-info/requires.txt
il2fb_ds_config.egg-info/top_level.txt
requirements/dist.txt