Metadata-Version: 1.1
Name: il2fb-ds-config
Version: 1.0.0
Summary: Library for working with settings of IL-2 FB Dedicated Server
Home-page: https://github.com/IL2HorusTeam/il2fb-ds-config
Author: Alexander Oblovatniy
Author-email: oblovatniy@gmail.com
License: LGPLv3
Keywords: il2,il-2,fb,forgotten battles,server,dedicated,config,settings
Platform: UNKNOWN
Classifier: Development Status :: 5 - Production/Stable
Classifier: Intended Audience :: Developers
Classifier: License :: OSI Approved :: GNU Lesser General Public License v3 (LGPLv3)
Classifier: Natural Language :: English
Classifier: Operating System :: OS Independent
Classifier: Programming Language :: Python :: 2.7
Classifier: Programming Language :: Python :: 3.4
Classifier: Programming Language :: Python :: 3.5
Classifier: Programming Language :: Python :: 3.6
Classifier: Topic :: Software Development :: Libraries
